<Module>
	<Name value="BSI Cloak and Dagger: CivilWar"/>
	<Id value="BSI.CloakDagger.CivilWar"/>
	<Version value="v0.1.0"/>
	<Official value="false" />
	<DefaultModule value="false" />
	<SingleplayerModule value="true"/>
	<MultiplayerModule value="false"/>
	<DependedModules>
		<DependedModule Id="Bannerlord.MBOptionScreen"/>
		<DependedModule Id="Native"/>
		<DependedModule Id="SandBoxCore"/>
		<DependedModule Id="Sandbox"/>
		<DependedModule Id="StoryMode" />
		<DependedModule Id="BSI.CloakDagger"/>
	</DependedModules>
	<SubModules>
		<SubModule>
			<Name value="BSI Cloak and Dagger: CivilWar"/>
			<DLLName value="BSI.CloakDagger.CivilWar.dll"/>
			<SubModuleClassType value="BSI.CloakDagger.CivilWar.SubModule"/>
			<Tags>
				<Tag key="DedicatedServerType" value="none" />
				<Tag key="IsNoRenderModeElement" value="false" />
			</Tags>
		</SubModule>
	</SubModules>
	<Xmls/>
</Module>